shortcode/__init__.py
shortcode/plugin.py
mkdocs_shortcode-0.0.2.dist-info/LICENSE
mkdocs_shortcode-0.0.2.dist-info/METADATA
mkdocs_shortcode-0.0.2.dist-info/WHEEL
mkdocs_shortcode-0.0.2.dist-info/entry_points.txt
mkdocs_shortcode-0.0.2.dist-info/top_level.txt
mkdocs_shortcode-0.0.2.dist-info/RECORD
