Metadata-Version: 2.1
Name: mkdocs-shortcode
Version: 0.0.2
Summary: Add Shortcodes and Templates to mkdocs
Home-page: UNKNOWN
Author: Thomas Deniffel
Author-email: tdeniffel@gmail.com
License: Apache2
Platform: UNKNOWN
Classifier: Development Status :: 4 - Beta
Classifier: Intended Audience :: Developers
Classifier: Programming Language :: Python
Classifier: Programming Language :: Python :: 3 :: Only
Classifier: Programming Language :: Python :: 3.6
Classifier: Programming Language :: Python :: 3.7
Requires-Python: >=3
Requires-Dist: mkdocs (>=1.0.4)
